MANIFEST.in
README.md
readme.md
requirements.txt
setup.py
rosey_graph/__init__.py
rosey_graph/notebook.py
rosey_graph.egg-info/PKG-INFO
rosey_graph.egg-info/SOURCES.txt
rosey_graph.egg-info/dependency_links.txt
rosey_graph.egg-info/not-zip-safe
rosey_graph.egg-info/requires.txt
rosey_graph.egg-info/top_level.txt
tests/__init__.py
tests/test_plots.py