Metadata-Version: 2.1
Name: rosey-graph
Version: 1.2024.5.16
Summary: Making certain routine graphs more quickly
Home-page: https://github.com/arose13/rosey-graph
Author: Stephen Rose
Author-email: me@stephenro.se
License: BSD
Classifier: Development Status :: 4 - Beta
Classifier: Intended Audience :: Developers
Classifier: Programming Language :: Python :: 3
Classifier: Topic :: Scientific/Engineering :: Artificial Intelligence
Requires-Dist: matplotlib
Requires-Dist: seaborn
Requires-Dist: scikit-learn
